LICENSE.md
MANIFEST.in
README.rst
setup.py
ansible_test/__init__.py
ansible_test/resources/Dockerfile.j2
ansible_test/resources/ansible.cfg.j2
ansible_test/resources/inventory.ini
ansible_test_tool.egg-info/PKG-INFO
ansible_test_tool.egg-info/SOURCES.txt
ansible_test_tool.egg-info/dependency_links.txt
ansible_test_tool.egg-info/requires.txt
ansible_test_tool.egg-info/top_level.txt
bin/ansible-test