Metadata-Version: 1.1
Name: ansible-test-tool
Version: 1.0.0
Summary: An ansible testing framework
Home-page: https://github.com/Nitaco/ansible-test.git
Author: Lukas Beumer
Author-email: lukas@familie-beumer.de
License: UNKNOWN
Download-URL: https://github.com/peterldowns/mypackage/archive/1.0.0.tar.gz
Keywords: testing,ansible,framework,roles
Platform: UNKNOWN
